fs/filefs/__init__.py
fs/filefs/filefs.py
fs_filefs-1.0.3.dist-info/licenses/LICENSE
fs_filefs-1.0.3.dist-info/METADATA
fs_filefs-1.0.3.dist-info/WHEEL
fs_filefs-1.0.3.dist-info/top_level.txt
fs_filefs-1.0.3.dist-info/RECORD
