Metadata-Version: 2.4
Name: fs.filefs
Version: 1.0.3
Summary: A custom filesystem for pyfilesystem2 that allows mounting files from other filesystems.
Maintainer-email: Andreas Bichinger <andreas.bichinger@gmail.com>
License-Expression: MIT
Project-URL: Homepage, https://github.com/abichinger/fs.filefs
Project-URL: Issues, https://github.com/abichinger/fs.filefs/issues
Keywords: pyfilesystem,filesystem,fs
Classifier: Programming Language :: Python :: 3
Classifier: Operating System :: OS Independent
Requires-Python: >=3.9
License-File: LICENSE
Requires-Dist: fs>=2.4.16
Dynamic: license-file
